mysql_f/__init__.py
mysql_f/mysql_f.py
mysql_f-0.1.4.dist-info/LICENSE
mysql_f-0.1.4.dist-info/METADATA
mysql_f-0.1.4.dist-info/WHEEL
mysql_f-0.1.4.dist-info/top_level.txt
mysql_f-0.1.4.dist-info/RECORD
