Metadata-Version: 2.2
Name: mysql_f
Version: 0.1.4
Summary: 高性能MySQL操作工具类库
Home-page: https://github.com/cxfjh/mysql_f
Author: fjh
Author-email: 2449579731@qq.com
Classifier: Development Status :: 3 - Alpha
Classifier: Intended Audience :: Developers
Classifier: License :: OSI Approved :: MIT License
Classifier: Programming Language :: Python :: 3
Classifier: Programming Language :: Python :: 3.7
Classifier: Programming Language :: Python :: 3.8
Classifier: Programming Language :: Python :: 3.9
Classifier: Programming Language :: Python :: 3.10
Requires-Python: >=3.7
License-File: LICENSE
Requires-Dist: mysqlclient>=2.1.0
Requires-Dist: dbutils>=3.0.0
Dynamic: author
Dynamic: author-email
Dynamic: classifier
Dynamic: description
Dynamic: description-content-type
Dynamic: home-page
Dynamic: requires-dist
Dynamic: requires-python
Dynamic: summary
